{"v":3,"stories":{"datetime-input--basic":{"id":"datetime-input--basic","name":"Basic","title":"Datetime Input","importPath":"./stories/cosmoz-datetime-input.stories.js","tags":["story"],"kind":"Datetime Input","story":"Basic","parameters":{"__id":"datetime-input--basic","docsOnly":false,"fileName":"./stories/cosmoz-datetime-input.stories.js"}},"datetime-input--min-max":{"id":"datetime-input--min-max","name":"Min Max","title":"Datetime Input","importPath":"./stories/cosmoz-datetime-input.stories.js","tags":["story"],"kind":"Datetime Input","story":"Min Max","parameters":{"__id":"datetime-input--min-max","docsOnly":false,"fileName":"./stories/cosmoz-datetime-input.stories.js"}}}}
